odoo10_addon_connector-10.0.2.1.1-py3.8-nspkg.pth
odoo/addons/connector/AUTHORS
odoo/addons/connector/CHANGES.rst
odoo/addons/connector/README.rst
odoo/addons/connector/__init__.py
odoo/addons/connector/__manifest__.py
odoo/addons/connector/backend.py
odoo/addons/connector/backend_model.py
odoo/addons/connector/connector.py
odoo/addons/connector/connector_menu.xml
odoo/addons/connector/event.py
odoo/addons/connector/exception.py
odoo/addons/connector/producer.py
odoo/addons/connector/res_partner_view.xml
odoo/addons/connector/setting.py
odoo/addons/connector/setting_view.xml
odoo/addons/connector/checkpoint/__init__.py
odoo/addons/connector/checkpoint/checkpoint.py
odoo/addons/connector/checkpoint/checkpoint_view.xml
odoo/addons/connector/components/__init__.py
odoo/addons/connector/components/backend_adapter.py
odoo/addons/connector/components/binder.py
odoo/addons/connector/components/core.py
odoo/addons/connector/components/listener.py
odoo/addons/connector/components/mapper.py
odoo/addons/connector/components/synchronizer.py
odoo/addons/connector/doc/Makefile
odoo/addons/connector/doc/bazaar
odoo/addons/connector/doc/conf.py
odoo/addons/connector/doc/index.rst
odoo/addons/connector/doc/make.bat
odoo/addons/connector/doc/_static/09_datamodel.png
odoo/addons/connector/doc/_static/connector_style.css
odoo/addons/connector/doc/_static/img/LogicSupply_Orange_260x80_transparent.png
odoo/addons/connector/doc/_static/img/akretion_logo.png
odoo/addons/connector/doc/_static/img/c2c_square_baseline_192.jpg
odoo/addons/connector/doc/_static/img/logo-debonix.jpg
odoo/addons/connector/doc/_static/img/magentoerpconnect.png
odoo/addons/connector/doc/_static/img/magentoerpconnect150.png
odoo/addons/connector/doc/_static/img/prestashoperpconnect.png
odoo/addons/connector/doc/_static/img/prestashoperpconnect150.png
odoo/addons/connector/doc/_templates/layout.html
odoo/addons/connector/doc/_templates/navbar.html
odoo/addons/connector/doc/_themes/.gitignore
odoo10_addon_connector-10.0.2.1.1.dist-info/METADATA
odoo10_addon_connector-10.0.2.1.1.dist-info/WHEEL
odoo10_addon_connector-10.0.2.1.1.dist-info/namespace_packages.txt
odoo10_addon_connector-10.0.2.1.1.dist-info/top_level.txt
odoo10_addon_connector-10.0.2.1.1.dist-info/RECORD
