Metadata-Version: 2.1
Name: odoo10-addon-connector
Version: 10.0.2.1.1
Summary: Connector
Home-page: http://odoo-connector.com
Author: Camptocamp,Openerp Connector Core Editors,Odoo Community Association (OCA)
Author-email: support@odoo-community.org
License: LGPL-3
Platform: UNKNOWN
Classifier: Programming Language :: Python
Classifier: Framework :: Odoo
Classifier: License :: OSI Approved :: GNU Lesser General Public License v3 (LGPLv3)
Requires-Python: ~=2.7
Requires-Dist: odoo10-addon-component
Requires-Dist: odoo10-addon-component-event
Requires-Dist: odoo10-addon-queue-job
Requires-Dist: odoo (<10.1dev,>=10.0)
